{
"date": "2026-02-04",
"games": {
"202602040HOU": [
{
"player": "Kevin Durant",
"abbr": "HOU",
"mp": 32.6,
"proj": {
"pts": 25.299999237060547,
"reb": 5.300000190734863,
"ast": 5.0,
"stl": 0.8999999761581421,
"blk": 0.7,
"fg3m": 2.4000000953674316
},
"actual": {
"pts": 15,
"reb": 5,
"ast": 1,
"stl": 2,
"blk": 1,
"fg3m": 0
}
},
{
"player": "Alperen \u00c5\u009eeng\u00c3\u00bcn",
"abbr": "HOU",
"mp": 31.0,
"proj": {
"pts": 21.100000381469727,
"reb": 10.100000381469727,
"ast": 6.099999904632568,
"stl": 1.2000000476837158,
"blk": 0.7,
"fg3m": 0.6000000238418579
},
"actual": {
"pts": 13,
"reb": 9,
"ast": 3,
"stl": 2,
"blk": 1,
"fg3m": 0
}
},
{
"player": "Amen Thompson",
"abbr": "HOU",
"mp": 28.6,
"proj": {
"pts": 17.399999618530273,
"reb": 8.300000190734863,
"ast": 6.0,
"stl": 1.399999976158142,
"blk": 1.0,
"fg3m": 0.4000000059604645
},
"actual": {
"pts": 11,
"reb": 4,
"ast": 4,
"stl": 1,
"blk": 0,
"fg3m": 1
}
},
{
"player": "Payton Pritchard",
"abbr": "BOS",
"mp": 33.5,
"proj": {
"pts": 16.0,
"reb": 3.799999952316284,
"ast": 5.300000190734863,
"stl": 0.699999988079071,
"blk": 0.0,
"fg3m": 2.5
},
"actual": {
"pts": 27,
"reb": 3,
"ast": 7,
"stl": 0,
"blk": 0,
"fg3m": 5
}
},
{
"player": "Derrick White",
"abbr": "BOS",
"mp": 37.1,
"proj": {
"pts": 15.600000381469727,
"reb": 4.300000190734863,
"ast": 5.800000190734863,
"stl": 1.100000023841858,
"blk": 0.6,
"fg3m": 2.5
},
"actual": {
"pts": 28,
"reb": 1,
"ast": 8,
"stl": 0,
"blk": 0,
"fg3m": 6
}
},
{
"player": "Jabari Smith Jr.",
"abbr": "HOU",
"mp": 33.3,
"proj": {
"pts": 14.5,
"reb": 6.699999809265137,
"ast": 2.299999952316284,
"stl": 0.8999999761581421,
"blk": 1.6,
"fg3m": 2.0999999046325684
},
"actual": {
"pts": 13,
"reb": 4,
"ast": 3,
"stl": 0,
"blk": 1,
"fg3m": 3
}
},
{
"player": "Tari Eason",
"abbr": "HOU",
"mp": 27.6,
"proj": {
"pts": 12.699999809265137,
"reb": 6.300000190734863,
"ast": 1.600000023841858,
"stl": 1.2000000476837158,
"blk": 0.7,
"fg3m": 2.200000047683716
},
"actual": {
"pts": 10,
"reb": 4,
"ast": 1,
"stl": 0,
"blk": 0,
"fg3m": 2
}
},
{
"player": "Reed Sheppard",
"abbr": "HOU",
"mp": 18.9,
"proj": {
"pts": 12.399999618530273,
"reb": 2.799999952316284,
"ast": 2.799999952316284,
"stl": 1.100000023841858,
"blk": 0.7,
"fg3m": 2.200000047683716
},
"actual": {
"pts": 9,
"reb": 2,
"ast": 0,
"stl": 1,
"blk": 0,
"fg3m": 3
}
},
{
"player": "Neemias Queta",
"abbr": "BOS",
"mp": 38.9,
"proj": {
"pts": 10.399999618530273,
"reb": 8.0,
"ast": 1.899999976158142,
"stl": 0.800000011920929,
"blk": 1.6,
"fg3m": 0.0
},
"actual": {
"pts": 10,
"reb": 19,
"ast": 2,
"stl": 2,
"blk": 5,
"fg3m": 0
}
},
{
"player": "Luka Garza",
"abbr": "BOS",
"mp": 33.8,
"proj": {
"pts": 7.800000190734863,
"reb": 4.699999809265137,
"ast": 1.2000000476837158,
"stl": 0.5,
"blk": 0.6,
"fg3m": 0.800000011920929
},
"actual": {
"pts": 19,
"reb": 6,
"ast": 2,
"stl": 2,
"blk": 0,
"fg3m": 2
}
},
{
"player": "Aaron Holiday",
"abbr": "HOU",
"mp": 10.9,
"proj": {
"pts": 7.400000095367432,
"reb": 1.7000000476837158,
"ast": 1.2000000476837158,
"stl": 0.5,
"blk": 0.1,
"fg3m": 1.5
},
"actual": {
"pts": 9,
"reb": 2,
"ast": 2,
"stl": 1,
"blk": 0,
"fg3m": 1
}
},
{
"player": "Baylor Scheierman",
"abbr": "BOS",
"mp": 23.0,
"proj": {
"pts": 6.5,
"reb": 3.4000000953674316,
"ast": 1.2999999523162842,
"stl": 0.6000000238418579,
"blk": 0.1,
"fg3m": 1.2999999523162842
},
"actual": {
"pts": 15,
"reb": 10,
"ast": 4,
"stl": 1,
"blk": 0,
"fg3m": 3
}
},
{
"player": "Hugo Gonz\u00c3\u00a1lez",
"abbr": "BOS",
"mp": 15.3,
"proj": {
"pts": 5.800000190734863,
"reb": 3.700000047683716,
"ast": 1.0,
"stl": 0.699999988079071,
"blk": 0.3,
"fg3m": 0.699999988079071
},
"actual": {
"pts": 2,
"reb": 3,
"ast": 0,
"stl": 0,
"blk": 0,
"fg3m": 0
}
},
{
"player": "Clint Capela",
"abbr": "HOU",
"mp": 14.9,
"proj": {
"pts": 5.699999809265137,
"reb": 5.900000095367432,
"ast": 0.8999999761581421,
"stl": 0.5,
"blk": 1.4,
"fg3m": 0.0
},
"actual": {
"pts": 4,
"reb": 5,
"ast": 0,
"stl": 1,
"blk": 0,
"fg3m": 0
}
},
{
"player": "Jordan Walsh",
"abbr": "BOS",
"mp": 14.7,
"proj": {
"pts": 5.300000190734863,
"reb": 3.799999952316284,
"ast": 1.0,
"stl": 0.699999988079071,
"blk": 0.6,
"fg3m": 0.699999988079071
},
"actual": {
"pts": 2,
"reb": 4,
"ast": 0,
"stl": 1,
"blk": 0,
"fg3m": 0
}
},
{
"player": "Isaiah Crawford",
"abbr": "HOU",
"mp": 5.7,
"proj": null,
"reason": "below_floor",
"actual": {
"pts": 2,
"reb": 1,
"ast": 0,
"stl": 0,
"blk": 2,
"fg3m": 0
}
},
{
"player": "JD Davison",
"abbr": "HOU",
"mp": 7.0,
"proj": null,
"reason": "below_floor",
"actual": {
"pts": 2,
"reb": 1,
"ast": 2,
"stl": 0,
"blk": 0,
"fg3m": 0
}
},
{
"player": "Jeff Green",
"abbr": "HOU",
"mp": 5.7,
"proj": null,
"reason": "below_floor",
"actual": {
"pts": 3,
"reb": 0,
"ast": 0,
"stl": 0,
"blk": 0,
"fg3m": 1
}
},
{
"player": "Ron Harper Jr.",
"abbr": "BOS",
"mp": 33.3,
"proj": null,
"reason": "insufficient_history",
"actual": {
"pts": 11,
"reb": 9,
"ast": 3,
"stl": 0,
"blk": 0,
"fg3m": 3
}
},
{
"player": "Josh Minott",
"abbr": "BOS",
"mp": 7.1,
"proj": null,
"reason": "below_floor",
"actual": {
"pts": 0,
"reb": 2,
"ast": 0,
"stl": 0,
"blk": 1,
"fg3m": 0
}
},
{
"player": "Josh Okogie",
"abbr": "HOU",
"mp": 16.6,
"proj": null,
"reason": "insufficient_history",
"actual": {
"pts": 2,
"reb": 1,
"ast": 0,
"stl": 1,
"blk": 0,
"fg3m": 0
}
},
{
"player": "Max Shulga",
"abbr": "BOS",
"mp": 1.7,
"proj": null,
"reason": "below_floor",
"actual": {
"pts": 0,
"reb": 0,
"ast": 0,
"stl": 0,
"blk": 0,
"fg3m": 0
}
},
{
"player": "Jae'Sean Tate",
"abbr": "HOU",
"mp": 7.2,
"proj": null,
"reason": "below_floor",
"actual": {
"pts": 0,
"reb": 0,
"ast": 0,
"stl": 1,
"blk": 0,
"fg3m": 0
}
},
{
"player": "Xavier Tillman Sr.",
"abbr": "BOS",
"mp": 1.7,
"proj": null,
"reason": "below_floor",
"actual": {
"pts": 0,
"reb": 0,
"ast": 0,
"stl": 0,
"blk": 0,
"fg3m": 0
}
}
],
"202602040LAC": [
{
"player": "Kawhi Leonard",
"abbr": "LAC",
"mp": 26.6,
"proj": {
"pts": 26.700000762939453,
"reb": 5.699999809265137,
"ast": 4.900000095367432,
"stl": 1.399999976158142,
"blk": 0.3,
"fg3m": 2.700000047683716
},
"actual": {
"pts": 25,
"reb": 7,
"ast": 4,
"stl": 1,
"blk": 0,
"fg3m": 2
}
},
{
"player": "Donovan Mitchell",
"abbr": "CLE",
"mp": 30.1,
"proj": {
"pts": 26.600000381469727,
"reb": 4.199999809265137,
"ast": 6.199999809265137,
"stl": 1.2999999523162842,
"blk": 0.1,
"fg3m": 3.5999999046325684
},
"actual": {
"pts": 29,
"reb": 5,
"ast": 9,
"stl": 4,
"blk": 0,
"fg3m": 3
}
},
{
"player": "Jarrett Allen",
"abbr": "CLE",
"mp": 23.4,
"proj": {
"pts": 15.300000190734863,
"reb": 8.699999809265137,
"ast": 2.299999952316284,
"stl": 0.8999999761581421,
"blk": 1.4,
"fg3m": 0.0
},
"actual": {
"pts": 10,
"reb": 11,
"ast": 3,
"stl": 2,
"blk": 1,
"fg3m": 0
}
},
{
"player": "Jaylon Tyson",
"abbr": "CLE",
"mp": 24.5,
"proj": {
"pts": 14.699999809265137,
"reb": 5.400000095367432,
"ast": 3.0,
"stl": 0.8999999761581421,
"blk": 0.1,
"fg3m": 2.0999999046325684
},
"actual": {
"pts": 17,
"reb": 4,
"ast": 1,
"stl": 1,
"blk": 0,
"fg3m": 3
}
},
{
"player": "John Collins",
"abbr": "LAC",
"mp": 27.1,
"proj": {
"pts": 13.600000381469727,
"reb": 5.300000190734863,
"ast": 1.600000023841858,
"stl": 0.800000011920929,
"blk": 0.1,
"fg3m": 1.600000023841858
},
"actual": {
"pts": 19,
"reb": 7,
"ast": 0,
"stl": 0,
"blk": 0,
"fg3m": 0
}
},
{
"player": "Dennis Schr\u00c3\u00b6der",
"abbr": "CLE",
"mp": 19.2,
"proj": {
"pts": 13.100000381469727,
"reb": 2.9000000953674316,
"ast": 4.199999809265137,
"stl": 0.800000011920929,
"blk": 0.1,
"fg3m": 1.7999999523162842
},
"actual": {
"pts": 11,
"reb": 2,
"ast": 6,
"stl": 3,
"blk": 0,
"fg3m": 1
}
},
{
"player": "Sam Merrill",
"abbr": "CLE",
"mp": 21.1,
"proj": {
"pts": 12.199999809265137,
"reb": 2.4000000953674316,
"ast": 2.700000047683716,
"stl": 0.6000000238418579,
"blk": 0.1,
"fg3m": 2.700000047683716
},
"actual": {
"pts": 11,
"reb": 1,
"ast": 0,
"stl": 0,
"blk": 0,
"fg3m": 3
}
},
{
"player": "Jordan Miller",
"abbr": "LAC",
"mp": 29.7,
"proj": {
"pts": 11.899999618530273,
"reb": 3.9000000953674316,
"ast": 1.899999976158142,
"stl": 0.800000011920929,
"blk": 0.1,
"fg3m": 1.100000023841858
},
"actual": {
"pts": 5,
"reb": 4,
"ast": 3,
"stl": 1,
"blk": 0,
"fg3m": 1
}
},
{
"player": "Kobe Sanders",
"abbr": "LAC",
"mp": 20.0,
"proj": {
"pts": 9.600000381469727,
"reb": 2.799999952316284,
"ast": 2.0,
"stl": 0.6000000238418579,
"blk": 0.0,
"fg3m": 1.5
},
"actual": {
"pts": 4,
"reb": 2,
"ast": 2,
"stl": 1,
"blk": 0,
"fg3m": 0
}
},
{
"player": "Derrick Jones Jr.",
"abbr": "LAC",
"mp": 21.4,
"proj": {
"pts": 8.899999618530273,
"reb": 3.0,
"ast": 1.2000000476837158,
"stl": 0.699999988079071,
"blk": 1.3,
"fg3m": 1.2000000476837158
},
"actual": {
"pts": 7,
"reb": 2,
"ast": 0,
"stl": 0,
"blk": 1,
"fg3m": 0
}
},
{
"player": "Nae'Qwan Tomlin",
"abbr": "CLE",
"mp": 20.3,
"proj": {
"pts": 8.5,
"reb": 3.700000047683716,
"ast": 1.2999999523162842,
"stl": 0.800000011920929,
"blk": 0.3,
"fg3m": 0.699999988079071
},
"actual": {
"pts": 4,
"reb": 1,
"ast": 2,
"stl": 2,
"blk": 2,
"fg3m": 0
}
},
{
"player": "Kris Dunn",
"abbr": "LAC",
"mp": 20.5,
"proj": {
"pts": 8.300000190734863,
"reb": 2.9000000953674316,
"ast": 3.4000000953674316,
"stl": 1.0,
"blk": 0.1,
"fg3m": 1.100000023841858
},
"actual": {
"pts": 2,
"reb": 3,
"ast": 6,
"stl": 1,
"blk": 0,
"fg3m": 0
}
},
{
"player": "Thomas Bryant",
"abbr": "CLE",
"mp": 16.5,
"proj": {
"pts": 8.300000190734863,
"reb": 4.699999809265137,
"ast": 1.2999999523162842,
"stl": 0.4000000059604645,
"blk": 0.7,
"fg3m": 1.100000023841858
},
"actual": {
"pts": 8,
"reb": 8,
"ast": 0,
"stl": 0,
"blk": 2,
"fg3m": 0
}
},
{
"player": "Bogdan Bogdanovi\u00c4\u0087",
"abbr": "LAC",
"mp": 11.9,
"proj": {
"pts": 7.5,
"reb": 2.5999999046325684,
"ast": 2.299999952316284,
"stl": 0.5,
"blk": 0.0,
"fg3m": 1.399999976158142
},
"actual": {
"pts": 2,
"reb": 1,
"ast": 1,
"stl": 0,
"blk": 0,
"fg3m": 0
}
},
{
"player": "Kobe Brown",
"abbr": "LAC",
"mp": 8.9,
"proj": {
"pts": 6.099999904632568,
"reb": 3.299999952316284,
"ast": 1.2999999523162842,
"stl": 0.6000000238418579,
"blk": 0.3,
"fg3m": 0.8999999761581421
},
"actual": {
"pts": 10,
"reb": 0,
"ast": 0,
"stl": 0,
"blk": 0,
"fg3m": 2
}
},
{
"player": "Keon Ellis",
"abbr": "CLE",
"mp": 18.5,
"proj": {
"pts": 6.0,
"reb": 2.200000047683716,
"ast": 1.0,
"stl": 1.0,
"blk": 0.7,
"fg3m": 1.399999976158142
},
"actual": {
"pts": 6,
"reb": 3,
"ast": 0,
"stl": 2,
"blk": 0,
"fg3m": 2
}
},
{
"player": "Craig Porter Jr.",
"abbr": "CLE",
"mp": 24.8,
"proj": {
"pts": 5.900000095367432,
"reb": 3.4000000953674316,
"ast": 3.5,
"stl": 1.0,
"blk": 0.9,
"fg3m": 0.699999988079071
},
"actual": {
"pts": 7,
"reb": 2,
"ast": 2,
"stl": 1,
"blk": 0,
"fg3m": 1
}
},
{
"player": "Cam Christie",
"abbr": "LAC",
"mp": 12.0,
"proj": {
"pts": 5.900000095367432,
"reb": 2.9000000953674316,
"ast": 1.100000023841858,
"stl": 0.5,
"blk": 0.0,
"fg3m": 0.6000000238418579
},
"actual": {
"pts": 2,
"reb": 1,
"ast": 0,
"stl": 1,
"blk": 1,
"fg3m": 0
}
},
{
"player": "Dean Wade",
"abbr": "CLE",
"mp": 19.6,
"proj": {
"pts": 5.699999809265137,
"reb": 4.099999904632568,
"ast": 1.600000023841858,
"stl": 0.800000011920929,
"blk": 0.6,
"fg3m": 1.100000023841858
},
"actual": {
"pts": 5,
"reb": 3,
"ast": 3,
"stl": 1,
"blk": 0,
"fg3m": 1
}
},
{
"player": "Yanic Konan Niederh\u00c3\u00a4user",
"abbr": "LAC",
"mp": 24.9,
"proj": {
"pts": 5.5,
"reb": 3.799999952316284,
"ast": 0.699999988079071,
"stl": 0.4000000059604645,
"blk": 1.1,
"fg3m": 0.0
},
"actual": {
"pts": 10,
"reb": 8,
"ast": 0,
"stl": 0,
"blk": 2,
"fg3m": 0
}
},
{
"player": "Larry Nance Jr.",
"abbr": "CLE",
"mp": 8.1,
"proj": {
"pts": 5.099999904632568,
"reb": 3.0999999046325684,
"ast": 1.100000023841858,
"stl": 0.699999988079071,
"blk": 0.0,
"fg3m": 0.800000011920929
},
"actual": {
"pts": 8,
"reb": 1,
"ast": 1,
"stl": 0,
"blk": 0,
"fg3m": 2
}
},
{
"player": "Nicolas Batum",
"abbr": "LAC",
"mp": 5.8,
"proj": null,
"reason": "below_floor",
"actual": {
"pts": 0,
"reb": 0,
"ast": 0,
"stl": 0,
"blk": 0,
"fg3m": 0
}
},
{
"player": "Tristan Enaruna",
"abbr": "CLE",
"mp": 7.0,
"proj": null,
"reason": "below_floor",
"actual": {
"pts": 2,
"reb": 3,
"ast": 1,
"stl": 0,
"blk": 0,
"fg3m": 0
}
},
{
"player": "Brook Lopez",
"abbr": "LAC",
"mp": 23.1,
"proj": null,
"reason": "insufficient_history",
"actual": {
"pts": 5,
"reb": 2,
"ast": 1,
"stl": 1,
"blk": 0,
"fg3m": 1
}
},
{
"player": "Tyrese Proctor",
"abbr": "CLE",
"mp": 7.0,
"proj": null,
"reason": "below_floor",
"actual": {
"pts": 6,
"reb": 0,
"ast": 2,
"stl": 1,
"blk": 0,
"fg3m": 0
}
},
{
"player": "TyTy Washington Jr.",
"abbr": "LAC",
"mp": 8.1,
"proj": null,
"reason": "insufficient_history",
"actual": {
"pts": 0,
"reb": 0,
"ast": 3,
"stl": 0,
"blk": 0,
"fg3m": 0
}
}
],
"202602040MIL": [
{
"player": "Trey Murphy III",
"abbr": "NOP",
"mp": 39.9,
"proj": {
"pts": 21.600000381469727,
"reb": 5.400000095367432,
"ast": 3.700000047683716,
"stl": 1.2999999523162842,
"blk": 0.6,
"fg3m": 3.0
},
"actual": {
"pts": 44,
"reb": 6,
"ast": 6,
"stl": 3,
"blk": 0,
"fg3m": 12
}
},
{
"player": "Zion Williamson",
"abbr": "NOP",
"mp": 37.7,
"proj": {
"pts": 19.600000381469727,
"reb": 7.400000095367432,
"ast": 3.299999952316284,
"stl": 0.8999999761581421,
"blk": 1.0,
"fg3m": 0.0
},
"actual": {
"pts": 20,
"reb": 5,
"ast": 8,
"stl": 2,
"blk": 0,
"fg3m": 0
}
},
{
"player": "Kyle Kuzma",
"abbr": "MIL",
"mp": 31.0,
"proj": {
"pts": 17.399999618530273,
"reb": 5.900000095367432,
"ast": 3.700000047683716,
"stl": 0.8999999761581421,
"blk": 0.3,
"fg3m": 1.2999999523162842
},
"actual": {
"pts": 7,
"reb": 6,
"ast": 9,
"stl": 0,
"blk": 0,
"fg3m": 1
}
},
{
"player": "Ryan Rollins",
"abbr": "MIL",
"mp": 39.8,
"proj": {
"pts": 17.100000381469727,
"reb": 4.599999904632568,
"ast": 6.199999809265137,
"stl": 1.5,
"blk": 0.4,
"fg3m": 2.5999999046325684
},
"actual": {
"pts": 27,
"reb": 4,
"ast": 4,
"stl": 0,
"blk": 0,
"fg3m": 3
}
},
{
"player": "Saddiq Bey",
"abbr": "NOP",
"mp": 35.1,
"proj": {
"pts": 17.0,
"reb": 5.599999904632568,
"ast": 3.0,
"stl": 0.8999999761581421,
"blk": 0.0,
"fg3m": 2.0
},
"actual": {
"pts": 22,
"reb": 3,
"ast": 2,
"stl": 0,
"blk": 0,
"fg3m": 4
}
},
{
"player": "Myles Turner",
"abbr": "MIL",
"mp": 28.5,
"proj": {
"pts": 14.600000381469727,
"reb": 5.800000190734863,
"ast": 1.899999976158142,
"stl": 0.800000011920929,
"blk": 2.1,
"fg3m": 2.200000047683716
},
"actual": {
"pts": 16,
"reb": 9,
"ast": 1,
"stl": 0,
"blk": 2,
"fg3m": 2
}
},
{
"player": "Kevin Porter Jr.",
"abbr": "MIL",
"mp": 29.4,
"proj": {
"pts": 14.100000381469727,
"reb": 4.599999904632568,
"ast": 5.599999904632568,
"stl": 1.5,
"blk": 0.6,
"fg3m": 1.7000000476837158
},
"actual": {
"pts": 18,
"reb": 6,
"ast": 9,
"stl": 5,
"blk": 0,
"fg3m": 0
}
},
{
"player": "Derik Queen",
"abbr": "NOP",
"mp": 22.0,
"proj": {
"pts": 12.800000190734863,
"reb": 7.599999904632568,
"ast": 4.300000190734863,
"stl": 1.0,
"blk": 0.9,
"fg3m": 0.30000001192092896
},
"actual": {
"pts": 6,
"reb": 3,
"ast": 7,
"stl": 0,
"blk": 0,
"fg3m": 0
}
},
{
"player": "Jeremiah Fears",
"abbr": "NOP",
"mp": 19.8,
"proj": {
"pts": 11.199999809265137,
"reb": 3.4000000953674316,
"ast": 2.4000000953674316,
"stl": 1.100000023841858,
"blk": 0.6,
"fg3m": 1.100000023841858
},
"actual": {
"pts": 13,
"reb": 2,
"ast": 4,
"stl": 1,
"blk": 0,
"fg3m": 3
}
},
{
"player": "A.J. Green",
"abbr": "MIL",
"mp": 35.8,
"proj": {
"pts": 11.199999809265137,
"reb": 3.0,
"ast": 1.899999976158142,
"stl": 0.699999988079071,
"blk": 0.3,
"fg3m": 2.9000000953674316
},
"actual": {
"pts": 20,
"reb": 3,
"ast": 2,
"stl": 0,
"blk": 0,
"fg3m": 6
}
},
{
"player": "Herbert Jones",
"abbr": "NOP",
"mp": 36.0,
"proj": {
"pts": 10.399999618530273,
"reb": 3.700000047683716,
"ast": 2.9000000953674316,
"stl": 1.2999999523162842,
"blk": 1.0,
"fg3m": 1.7999999523162842
},
"actual": {
"pts": 7,
"reb": 2,
"ast": 2,
"stl": 2,
"blk": 0,
"fg3m": 1
}
},
{
"player": "Gary Trent Jr.",
"abbr": "MIL",
"mp": 23.8,
"proj": {
"pts": 9.199999809265137,
"reb": 1.899999976158142,
"ast": 1.600000023841858,
"stl": 0.800000011920929,
"blk": 0.1,
"fg3m": 2.0999999046325684
},
"actual": {
"pts": 13,
"reb": 0,
"ast": 2,
"stl": 0,
"blk": 0,
"fg3m": 3
}
},
{
"player": "Jose Alvarado",
"abbr": "NOP",
"mp": 16.9,
"proj": {
"pts": 8.5,
"reb": 2.5999999046325684,
"ast": 3.4000000953674316,
"stl": 0.800000011920929,
"blk": 0.0,
"fg3m": 1.899999976158142
},
"actual": {
"pts": 9,
"reb": 5,
"ast": 1,
"stl": 0,
"blk": 0,
"fg3m": 3
}
},
{
"player": "Pete Nance",
"abbr": "MIL",
"mp": 18.7,
"proj": {
"pts": 8.300000190734863,
"reb": 4.0,
"ast": 1.2000000476837158,
"stl": 0.699999988079071,
"blk": 0.3,
"fg3m": 1.2999999523162842
},
"actual": {
"pts": 16,
"reb": 3,
"ast": 3,
"stl": 0,
"blk": 0,
"fg3m": 4
}
},
{
"player": "Yves Missi",
"abbr": "NOP",
"mp": 30.8,
"proj": {
"pts": 6.0,
"reb": 5.599999904632568,
"ast": 1.2999999523162842,
"stl": 0.4000000059604645,
"blk": 1.7,
"fg3m": 0.0
},
"actual": {
"pts": 7,
"reb": 7,
"ast": 1,
"stl": 0,
"blk": 2,
"fg3m": 0
}
},
{
"player": "Amir Coffey",
"abbr": "MIL",
"mp": 25.1,
"proj": {
"pts": 5.699999809265137,
"reb": 2.299999952316284,
"ast": 1.2999999523162842,
"stl": 0.6000000238418579,
"blk": 0.1,
"fg3m": 0.6000000238418579
},
"actual": {
"pts": 16,
"reb": 5,
"ast": 1,
"stl": 0,
"blk": 1,
"fg3m": 2
}
},
{
"player": "Micah Peavy",
"abbr": "NOP",
"mp": 11.6,
"proj": {
"pts": 5.599999904632568,
"reb": 2.299999952316284,
"ast": 1.100000023841858,
"stl": 0.800000011920929,
"blk": 0.1,
"fg3m": 0.699999988079071
},
"actual": {
"pts": 2,
"reb": 2,
"ast": 0,
"stl": 1,
"blk": 0,
"fg3m": 0
}
},
{
"player": "Karlo Matkovi\u00c4\u0087",
"abbr": "NOP",
"mp": 15.3,
"proj": {
"pts": 5.300000190734863,
"reb": 3.9000000953674316,
"ast": 1.100000023841858,
"stl": 0.5,
"blk": 0.9,
"fg3m": 0.6000000238418579
},
"actual": {
"pts": 7,
"reb": 3,
"ast": 1,
"stl": 0,
"blk": 0,
"fg3m": 1
}
},
{
"player": "Andre Jackson Jr.",
"abbr": "MIL",
"mp": 5.1,
"proj": null,
"reason": "below_floor",
"actual": {
"pts": 0,
"reb": 1,
"ast": 1,
"stl": 0,
"blk": 0,
"fg3m": 0
}
},
{
"player": "Jericho Sims",
"abbr": "MIL",
"mp": 27.8,
"proj": null,
"reason": "insufficient_history",
"actual": {
"pts": 8,
"reb": 6,
"ast": 4,
"stl": 0,
"blk": 0,
"fg3m": 0
}
}
],
"202602040NYK": [
{
"player": "Nikola Joki\u00c4\u0087",
"abbr": "DEN",
"mp": 44.6,
"proj": {
"pts": 27.899999618530273,
"reb": 12.199999809265137,
"ast": 9.199999809265137,
"stl": 1.399999976158142,
"blk": 0.4,
"fg3m": 1.7000000476837158
},
"actual": {
"pts": 30,
"reb": 14,
"ast": 10,
"stl": 0,
"blk": 0,
"fg3m": 1
}
},
{
"player": "Jalen Brunson",
"abbr": "NYK",
"mp": 47.0,
"proj": {
"pts": 25.899999618530273,
"reb": 3.299999952316284,
"ast": 6.300000190734863,
"stl": 0.800000011920929,
"blk": 0.3,
"fg3m": 2.9000000953674316
},
"actual": {
"pts": 42,
"reb": 8,
"ast": 9,
"stl": 2,
"blk": 0,
"fg3m": 5
}
},
{
"player": "Jamal Murray",
"abbr": "DEN",
"mp": 47.8,
"proj": {
"pts": 23.600000381469727,
"reb": 4.199999809265137,
"ast": 7.199999809265137,
"stl": 1.0,
"blk": 0.7,
"fg3m": 3.0
},
"actual": {
"pts": 39,
"reb": 5,
"ast": 6,
"stl": 1,
"blk": 0,
"fg3m": 3
}
},
{
"player": "Peyton Watson",
"abbr": "DEN",
"mp": 33.3,
"proj": {
"pts": 16.399999618530273,
"reb": 4.800000190734863,
"ast": 2.299999952316284,
"stl": 0.8999999761581421,
"blk": 2.0,
"fg3m": 1.899999976158142
},
"actual": {
"pts": 10,
"reb": 5,
"ast": 2,
"stl": 1,
"blk": 1,
"fg3m": 1
}
},
{
"player": "Karl-Anthony Towns",
"abbr": "NYK",
"mp": 31.0,
"proj": {
"pts": 16.299999237060547,
"reb": 12.899999618530273,
"ast": 2.9000000953674316,
"stl": 1.0,
"blk": 0.4,
"fg3m": 1.5
},
"actual": {
"pts": 24,
"reb": 12,
"ast": 1,
"stl": 0,
"blk": 0,
"fg3m": 2
}
},
{
"player": "OG Anunoby",
"abbr": "NYK",
"mp": 48.0,
"proj": {
"pts": 15.699999809265137,
"reb": 5.5,
"ast": 2.5999999046325684,
"stl": 1.399999976158142,
"blk": 0.6,
"fg3m": 2.200000047683716
},
"actual": {
"pts": 20,
"reb": 8,
"ast": 4,
"stl": 0,
"blk": 0,
"fg3m": 4
}
},
{
"player": "Mikal Bridges",
"abbr": "NYK",
"mp": 48.5,
"proj": {
"pts": 14.899999618530273,
"reb": 3.9000000953674316,
"ast": 4.199999809265137,
"stl": 1.2000000476837158,
"blk": 0.6,
"fg3m": 2.0999999046325684
},
"actual": {
"pts": 5,
"reb": 4,
"ast": 4,
"stl": 1,
"blk": 1,
"fg3m": 1
}
},
{
"player": "Tim Hardaway Jr.",
"abbr": "DEN",
"mp": 41.5,
"proj": {
"pts": 12.199999809265137,
"reb": 3.0,
"ast": 1.399999976158142,
"stl": 0.6000000238418579,
"blk": 0.1,
"fg3m": 2.5999999046325684
},
"actual": {
"pts": 19,
"reb": 6,
"ast": 2,
"stl": 1,
"blk": 0,
"fg3m": 4
}
},
{
"player": "Jonas Valan\u00c4\u008di\u00c5\u00abnas",
"abbr": "DEN",
"mp": 12.8,
"proj": {
"pts": 10.600000381469727,
"reb": 6.0,
"ast": 1.600000023841858,
"stl": 0.5,
"blk": 1.4,
"fg3m": 0.20000000298023224
},
"actual": {
"pts": 2,
"reb": 3,
"ast": 2,
"stl": 0,
"blk": 0,
"fg3m": 0
}
},
{
"player": "Landry Shamet",
"abbr": "NYK",
"mp": 35.9,
"proj": {
"pts": 9.399999618530273,
"reb": 2.299999952316284,
"ast": 1.2999999523162842,
"stl": 0.5,
"blk": 0.1,
"fg3m": 2.0999999046325684
},
"actual": {
"pts": 16,
"reb": 2,
"ast": 3,
"stl": 0,
"blk": 0,
"fg3m": 4
}
},
{
"player": "Jordan Clarkson",
"abbr": "NYK",
"mp": 23.7,
"proj": {
"pts": 9.399999618530273,
"reb": 2.200000047683716,
"ast": 1.5,
"stl": 0.5,
"blk": 0.1,
"fg3m": 1.399999976158142
},
"actual": {
"pts": 11,
"reb": 1,
"ast": 1,
"stl": 0,
"blk": 0,
"fg3m": 1
}
},
{
"player": "Julian Strawther",
"abbr": "DEN",
"mp": 16.9,
"proj": {
"pts": 8.600000381469727,
"reb": 2.799999952316284,
"ast": 1.600000023841858,
"stl": 0.6000000238418579,
"blk": 0.1,
"fg3m": 0.8999999761581421
},
"actual": {
"pts": 11,
"reb": 3,
"ast": 1,
"stl": 1,
"blk": 0,
"fg3m": 2
}
},
{
"player": "Christian Braun",
"abbr": "DEN",
"mp": 43.5,
"proj": {
"pts": 8.300000190734863,
"reb": 3.5,
"ast": 2.200000047683716,
"stl": 0.6000000238418579,
"blk": 0.4,
"fg3m": 0.800000011920929
},
"actual": {
"pts": 6,
"reb": 7,
"ast": 6,
"stl": 0,
"blk": 0,
"fg3m": 0
}
},
{
"player": "Bruce Brown",
"abbr": "DEN",
"mp": 37.7,
"proj": {
"pts": 8.199999809265137,
"reb": 3.700000047683716,
"ast": 2.0,
"stl": 0.8999999761581421,
"blk": 0.3,
"fg3m": 0.800000011920929
},
"actual": {
"pts": 10,
"reb": 5,
"ast": 0,
"stl": 3,
"blk": 1,
"fg3m": 2
}
},
{
"player": "Tyler Kolek",
"abbr": "NYK",
"mp": 12.7,
"proj": {
"pts": 7.900000095367432,
"reb": 2.200000047683716,
"ast": 3.9000000953674316,
"stl": 0.6000000238418579,
"blk": 0.0,
"fg3m": 1.100000023841858
},
"actual": {
"pts": 1,
"reb": 1,
"ast": 4,
"stl": 0,
"blk": 0,
"fg3m": 0
}
},
{
"player": "Spencer Jones",
"abbr": "DEN",
"mp": 12.0,
"proj": {
"pts": 6.599999904632568,
"reb": 3.5,
"ast": 1.100000023841858,
"stl": 0.8999999761581421,
"blk": 0.7,
"fg3m": 1.100000023841858
},
"actual": {
"pts": 0,
"reb": 3,
"ast": 0,
"stl": 1,
"blk": 1,
"fg3m": 0
}
},
{
"player": "Mohamed Diawara",
"abbr": "NYK",
"mp": 14.4,
"proj": {
"pts": 6.300000190734863,
"reb": 2.9000000953674316,
"ast": 1.399999976158142,
"stl": 0.699999988079071,
"blk": 0.3,
"fg3m": 1.2999999523162842
},
"actual": {
"pts": 5,
"reb": 0,
"ast": 0,
"stl": 0,
"blk": 0,
"fg3m": 1
}
},
{
"player": "Mitchell Robinson",
"abbr": "NYK",
"mp": 23.1,
"proj": {
"pts": 5.5,
"reb": 8.5,
"ast": 1.0,
"stl": 0.699999988079071,
"blk": 1.1,
"fg3m": 0.0
},
"actual": {
"pts": 10,
"reb": 8,
"ast": 0,
"stl": 1,
"blk": 1,
"fg3m": 0
}
},
{
"player": "Ariel Hukporti",
"abbr": "NYK",
"mp": 3.7,
"proj": null,
"reason": "below_floor",
"actual": {
"pts": 0,
"reb": 0,
"ast": 0,
"stl": 0,
"blk": 0,
"fg3m": 0
}
},
{
"player": "Kevin McCullar Jr.",
"abbr": "NYK",
"mp": 2.1,
"proj": null,
"reason": "below_floor",
"actual": {
"pts": 0,
"reb": 1,
"ast": 2,
"stl": 0,
"blk": 0,
"fg3m": 0
}
}
],
"202602040SAC": [
{
"player": "DeMar DeRozan",
"abbr": "SAC",
"mp": 27.6,
"proj": {
"pts": 20.799999237060547,
"reb": 3.5999999046325684,
"ast": 4.5,
"stl": 1.100000023841858,
"blk": 0.1,
"fg3m": 0.8999999761581421
},
"actual": {
"pts": 20,
"reb": 3,
"ast": 5,
"stl": 0,
"blk": 0,
"fg3m": 1
}
},
{
"player": "Zach LaVine",
"abbr": "SAC",
"mp": 22.2,
"proj": {
"pts": 20.600000381469727,
"reb": 3.0999999046325684,
"ast": 2.799999952316284,
"stl": 0.800000011920929,
"blk": 0.1,
"fg3m": 2.5999999046325684
},
"actual": {
"pts": 11,
"reb": 1,
"ast": 0,
"stl": 1,
"blk": 0,
"fg3m": 1
}
},
{
"player": "Russell Westbrook",
"abbr": "SAC",
"mp": 25.6,
"proj": {
"pts": 17.0,
"reb": 5.099999904632568,
"ast": 5.199999809265137,
"stl": 1.2000000476837158,
"blk": 0.1,
"fg3m": 2.0999999046325684
},
"actual": {
"pts": 13,
"reb": 0,
"ast": 5,
"stl": 1,
"blk": 0,
"fg3m": 3
}
},
{
"player": "Cedric Coward",
"abbr": "MEM",
"mp": 26.5,
"proj": {
"pts": 14.5,
"reb": 5.900000095367432,
"ast": 3.0,
"stl": 0.800000011920929,
"blk": 0.7,
"fg3m": 1.600000023841858
},
"actual": {
"pts": 5,
"reb": 7,
"ast": 6,
"stl": 0,
"blk": 1,
"fg3m": 0
}
},
{
"player": "Domantas Sabonis",
"abbr": "SAC",
"mp": 24.1,
"proj": {
"pts": 14.399999618530273,
"reb": 9.0,
"ast": 4.099999904632568,
"stl": 0.8999999761581421,
"blk": 0.3,
"fg3m": 0.30000001192092896
},
"actual": {
"pts": 24,
"reb": 15,
"ast": 3,
"stl": 1,
"blk": 0,
"fg3m": 0
}
},
{
"player": "Malik Monk",
"abbr": "SAC",
"mp": 17.9,
"proj": {
"pts": 13.600000381469727,
"reb": 2.5,
"ast": 3.200000047683716,
"stl": 0.699999988079071,
"blk": 0.6,
"fg3m": 2.200000047683716
},
"actual": {
"pts": 13,
"reb": 0,
"ast": 4,
"stl": 0,
"blk": 0,
"fg3m": 2
}
},
{
"player": "Santi Aldama",
"abbr": "MEM",
"mp": 24.1,
"proj": {
"pts": 12.600000381469727,
"reb": 6.199999809265137,
"ast": 2.5999999046325684,
"stl": 0.8999999761581421,
"blk": 0.7,
"fg3m": 1.600000023841858
},
"actual": {
"pts": 12,
"reb": 6,
"ast": 0,
"stl": 1,
"blk": 2,
"fg3m": 2
}
},
{
"player": "De'Andre Hunter",
"abbr": "SAC",
"mp": 26.4,
"proj": {
"pts": 12.600000381469727,
"reb": 3.700000047683716,
"ast": 1.899999976158142,
"stl": 0.699999988079071,
"blk": 0.1,
"fg3m": 1.899999976158142
},
"actual": {
"pts": 9,
"reb": 2,
"ast": 1,
"stl": 0,
"blk": 0,
"fg3m": 2
}
},
{
"player": "Jaylen Wells",
"abbr": "MEM",
"mp": 26.0,
"proj": {
"pts": 12.600000381469727,
"reb": 3.5,
"ast": 1.7999999523162842,
"stl": 0.8999999761581421,
"blk": 0.1,
"fg3m": 1.899999976158142
},
"actual": {
"pts": 18,
"reb": 3,
"ast": 1,
"stl": 0,
"blk": 0,
"fg3m": 6
}
},
{
"player": "GG Jackson II",
"abbr": "MEM",
"mp": 27.2,
"proj": {
"pts": 12.0,
"reb": 4.699999809265137,
"ast": 1.7000000476837158,
"stl": 0.699999988079071,
"blk": 1.0,
"fg3m": 1.100000023841858
},
"actual": {
"pts": 16,
"reb": 7,
"ast": 2,
"stl": 1,
"blk": 1,
"fg3m": 2
}
},
{
"player": "Cam Spencer",
"abbr": "MEM",
"mp": 26.9,
"proj": {
"pts": 10.899999618530273,
"reb": 2.799999952316284,
"ast": 5.699999809265137,
"stl": 0.800000011920929,
"blk": 0.3,
"fg3m": 1.899999976158142
},
"actual": {
"pts": 20,
"reb": 3,
"ast": 5,
"stl": 0,
"blk": 0,
"fg3m": 3
}
},
{
"player": "Maxime Raynaud",
"abbr": "SAC",
"mp": 20.8,
"proj": {
"pts": 10.300000190734863,
"reb": 7.199999809265137,
"ast": 1.2000000476837158,
"stl": 0.6000000238418579,
"blk": 0.6,
"fg3m": 0.30000001192092896
},
"actual": {
"pts": 6,
"reb": 5,
"ast": 0,
"stl": 0,
"blk": 0,
"fg3m": 0
}
},
{
"player": "Nique Clifford",
"abbr": "SAC",
"mp": 25.8,
"proj": {
"pts": 9.199999809265137,
"reb": 3.700000047683716,
"ast": 1.7000000476837158,
"stl": 0.800000011920929,
"blk": 0.4,
"fg3m": 1.2999999523162842
},
"actual": {
"pts": 14,
"reb": 3,
"ast": 5,
"stl": 0,
"blk": 0,
"fg3m": 2
}
},
{
"player": "Kentavious Caldwell-Pope",
"abbr": "MEM",
"mp": 22.5,
"proj": {
"pts": 8.300000190734863,
"reb": 2.5999999046325684,
"ast": 2.9000000953674316,
"stl": 0.800000011920929,
"blk": 0.0,
"fg3m": 1.0
},
"actual": {
"pts": 15,
"reb": 2,
"ast": 2,
"stl": 1,
"blk": 0,
"fg3m": 1
}
},
{
"player": "Devin Carter",
"abbr": "SAC",
"mp": 23.8,
"proj": {
"pts": 7.400000095367432,
"reb": 2.700000047683716,
"ast": 2.5,
"stl": 0.699999988079071,
"blk": 0.2,
"fg3m": 1.0
},
"actual": {
"pts": 10,
"reb": 6,
"ast": 5,
"stl": 1,
"blk": 1,
"fg3m": 0
}
},
{
"player": "Olivier-Maxence Prosper",
"abbr": "MEM",
"mp": 22.2,
"proj": {
"pts": 6.599999904632568,
"reb": 3.299999952316284,
"ast": 1.100000023841858,
"stl": 0.5,
"blk": 0.4,
"fg3m": 0.800000011920929
},
"actual": {
"pts": 8,
"reb": 5,
"ast": 0,
"stl": 1,
"blk": 0,
"fg3m": 0
}
},
{
"player": "Javon Small",
"abbr": "MEM",
"mp": 21.0,
"proj": {
"pts": 6.599999904632568,
"reb": 2.200000047683716,
"ast": 4.699999809265137,
"stl": 0.699999988079071,
"blk": 0.1,
"fg3m": 1.0
},
"actual": {
"pts": 5,
"reb": 6,
"ast": 2,
"stl": 0,
"blk": 0,
"fg3m": 1
}
},
{
"player": "Dylan Cardwell",
"abbr": "SAC",
"mp": 25.8,
"proj": null,
"reason": "insufficient_history",
"actual": {
"pts": 5,
"reb": 11,
"ast": 1,
"stl": 0,
"blk": 1,
"fg3m": 0
}
},
{
"player": "Ty Jerome",
"abbr": "MEM",
"mp": 20.7,
"proj": null,
"reason": "insufficient_history",
"actual": {
"pts": 28,
"reb": 1,
"ast": 7,
"stl": 1,
"blk": 0,
"fg3m": 3
}
},
{
"player": "Jahmai Mashack",
"abbr": "MEM",
"mp": 22.9,
"proj": null,
"reason": "insufficient_history",
"actual": {
"pts": 2,
"reb": 4,
"ast": 5,
"stl": 3,
"blk": 0,
"fg3m": 0
}
}
],
"202602040SAS": [
{
"player": "Victor Wembanyama",
"abbr": "SAS",
"mp": 28.4,
"proj": {
"pts": 21.200000762939453,
"reb": 11.800000190734863,
"ast": 3.200000047683716,
"stl": 1.0,
"blk": 3.0,
"fg3m": 1.5
},
"actual": {
"pts": 22,
"reb": 14,
"ast": 2,
"stl": 0,
"blk": 2,
"fg3m": 1
}
},
{
"player": "De'Aaron Fox",
"abbr": "SAS",
"mp": 33.2,
"proj": {
"pts": 18.299999237060547,
"reb": 3.9000000953674316,
"ast": 6.0,
"stl": 0.8999999761581421,
"blk": 0.3,
"fg3m": 2.0
},
"actual": {
"pts": 15,
"reb": 4,
"ast": 10,
"stl": 3,
"blk": 1,
"fg3m": 0
}
},
{
"player": "Stephon Castle",
"abbr": "SAS",
"mp": 26.5,
"proj": {
"pts": 16.399999618530273,
"reb": 4.900000095367432,
"ast": 6.0,
"stl": 1.0,
"blk": 0.4,
"fg3m": 1.2999999523162842
},
"actual": {
"pts": 14,
"reb": 3,
"ast": 4,
"stl": 3,
"blk": 2,
"fg3m": 0
}
},
{
"player": "Devin Vassell",
"abbr": "SAS",
"mp": 25.0,
"proj": {
"pts": 12.800000190734863,
"reb": 3.5,
"ast": 1.899999976158142,
"stl": 0.699999988079071,
"blk": 0.3,
"fg3m": 2.0999999046325684
},
"actual": {
"pts": 5,
"reb": 3,
"ast": 0,
"stl": 1,
"blk": 0,
"fg3m": 1
}
},
{
"player": "Keldon Johnson",
"abbr": "SAS",
"mp": 28.6,
"proj": {
"pts": 12.100000381469727,
"reb": 5.599999904632568,
"ast": 1.600000023841858,
"stl": 0.6000000238418579,
"blk": 0.4,
"fg3m": 1.2000000476837158
},
"actual": {
"pts": 25,
"reb": 6,
"ast": 2,
"stl": 0,
"blk": 1,
"fg3m": 4
}
},
{
"player": "Isaiah Joe",
"abbr": "OKC",
"mp": 37.1,
"proj": {
"pts": 10.300000190734863,
"reb": 2.4000000953674316,
"ast": 1.600000023841858,
"stl": 0.6000000238418579,
"blk": 0.1,
"fg3m": 2.0999999046325684
},
"actual": {
"pts": 2,
"reb": 5,
"ast": 2,
"stl": 1,
"blk": 2,
"fg3m": 0
}
},
{
"player": "Julian Champagnie",
"abbr": "SAS",
"mp": 27.4,
"proj": {
"pts": 10.199999809265137,
"reb": 5.300000190734863,
"ast": 1.5,
"stl": 0.699999988079071,
"blk": 0.4,
"fg3m": 2.0
},
"actual": {
"pts": 8,
"reb": 5,
"ast": 3,
"stl": 0,
"blk": 0,
"fg3m": 2
}
},
{
"player": "Aaron Wiggins",
"abbr": "OKC",
"mp": 37.7,
"proj": {
"pts": 10.199999809265137,
"reb": 3.700000047683716,
"ast": 1.7000000476837158,
"stl": 0.8999999761581421,
"blk": 0.6,
"fg3m": 1.899999976158142
},
"actual": {
"pts": 20,
"reb": 4,
"ast": 6,
"stl": 5,
"blk": 0,
"fg3m": 4
}
},
{
"player": "Harrison Barnes",
"abbr": "SAS",
"mp": 29.6,
"proj": {
"pts": 9.300000190734863,
"reb": 2.9000000953674316,
"ast": 1.7999999523162842,
"stl": 0.6000000238418579,
"blk": 0.3,
"fg3m": 1.600000023841858
},
"actual": {
"pts": 9,
"reb": 7,
"ast": 1,
"stl": 0,
"blk": 2,
"fg3m": 2
}
},
{
"player": "Cason Wallace",
"abbr": "OKC",
"mp": 34.4,
"proj": {
"pts": 9.100000381469727,
"reb": 2.9000000953674316,
"ast": 1.7999999523162842,
"stl": 1.2000000476837158,
"blk": 0.3,
"fg3m": 1.600000023841858
},
"actual": {
"pts": 13,
"reb": 3,
"ast": 5,
"stl": 3,
"blk": 1,
"fg3m": 1
}
},
{
"player": "Kenrich Williams",
"abbr": "OKC",
"mp": 35.2,
"proj": {
"pts": 7.599999904632568,
"reb": 3.5,
"ast": 1.7000000476837158,
"stl": 0.6000000238418579,
"blk": 0.1,
"fg3m": 0.8999999761581421
},
"actual": {
"pts": 25,
"reb": 9,
"ast": 2,
"stl": 1,
"blk": 0,
"fg3m": 4
}
},
{
"player": "Jaylin Williams",
"abbr": "OKC",
"mp": 39.7,
"proj": {
"pts": 6.800000190734863,
"reb": 4.900000095367432,
"ast": 2.200000047683716,
"stl": 0.699999988079071,
"blk": 1.0,
"fg3m": 1.2999999523162842
},
"actual": {
"pts": 24,
"reb": 12,
"ast": 4,
"stl": 0,
"blk": 2,
"fg3m": 4
}
},
{
"player": "Jordan McLaughlin",
"abbr": "SAS",
"mp": 12.9,
"proj": {
"pts": 6.300000190734863,
"reb": 2.0,
"ast": 1.7000000476837158,
"stl": 0.699999988079071,
"blk": 0.0,
"fg3m": 0.800000011920929
},
"actual": {
"pts": 3,
"reb": 1,
"ast": 1,
"stl": 1,
"blk": 0,
"fg3m": 1
}
},
{
"player": "Branden Carlson",
"abbr": "OKC",
"mp": 15.9,
"proj": {
"pts": 6.300000190734863,
"reb": 4.099999904632568,
"ast": 0.800000011920929,
"stl": 0.5,
"blk": 0.7,
"fg3m": 0.699999988079071
},
"actual": {
"pts": 3,
"reb": 7,
"ast": 0,
"stl": 0,
"blk": 2,
"fg3m": 1
}
},
{
"player": "Carter Bryant",
"abbr": "SAS",
"mp": 13.3,
"proj": {
"pts": 5.900000095367432,
"reb": 2.5999999046325684,
"ast": 0.800000011920929,
"stl": 0.5,
"blk": 0.4,
"fg3m": 0.800000011920929
},
"actual": {
"pts": 11,
"reb": 5,
"ast": 1,
"stl": 2,
"blk": 0,
"fg3m": 3
}
},
{
"player": "Chris Youngblood",
"abbr": "OKC",
"mp": 19.9,
"proj": {
"pts": 5.099999904632568,
"reb": 2.200000047683716,
"ast": 1.100000023841858,
"stl": 0.5,
"blk": 0.0,
"fg3m": 1.0
},
"actual": {
"pts": 5,
"reb": 3,
"ast": 2,
"stl": 0,
"blk": 2,
"fg3m": 1
}
},
{
"player": "Brooks Barnhizer",
"abbr": "OKC",
"mp": 20.0,
"proj": null,
"reason": "insufficient_history",
"actual": {
"pts": 14,
"reb": 3,
"ast": 5,
"stl": 0,
"blk": 0,
"fg3m": 4
}
},
{
"player": "Luke Kornet",
"abbr": "SAS",
"mp": 15.1,
"proj": null,
"reason": "insufficient_history",
"actual": {
"pts": 4,
"reb": 15,
"ast": 2,
"stl": 1,
"blk": 0,
"fg3m": 0
}
}
],
"202602040TOR": [
{
"player": "Anthony Edwards",
"abbr": "MIN",
"mp": 37.8,
"proj": {
"pts": 26.5,
"reb": 5.5,
"ast": 3.799999952316284,
"stl": 1.2999999523162842,
"blk": 0.7,
"fg3m": 3.0
},
"actual": {
"pts": 30,
"reb": 8,
"ast": 5,
"stl": 3,
"blk": 1,
"fg3m": 1
}
},
{
"player": "Brandon Ingram",
"abbr": "TOR",
"mp": 35.0,
"proj": {
"pts": 21.700000762939453,
"reb": 5.599999904632568,
"ast": 3.5999999046325684,
"stl": 0.8999999761581421,
"blk": 0.9,
"fg3m": 1.899999976158142
},
"actual": {
"pts": 25,
"reb": 6,
"ast": 4,
"stl": 0,
"blk": 1,
"fg3m": 3
}
},
{
"player": "Julius Randle",
"abbr": "MIN",
"mp": 35.6,
"proj": {
"pts": 21.100000381469727,
"reb": 6.699999809265137,
"ast": 5.300000190734863,
"stl": 1.100000023841858,
"blk": 0.4,
"fg3m": 1.7000000476837158
},
"actual": {
"pts": 17,
"reb": 4,
"ast": 4,
"stl": 0,
"blk": 0,
"fg3m": 1
}
},
{
"player": "Scottie Barnes",
"abbr": "TOR",
"mp": 36.6,
"proj": {
"pts": 19.899999618530273,
"reb": 9.0,
"ast": 5.699999809265137,
"stl": 1.2000000476837158,
"blk": 2.7,
"fg3m": 1.0
},
"actual": {
"pts": 22,
"reb": 10,
"ast": 8,
"stl": 1,
"blk": 1,
"fg3m": 0
}
},
{
"player": "RJ Barrett",
"abbr": "TOR",
"mp": 28.4,
"proj": {
"pts": 19.700000762939453,
"reb": 5.199999809265137,
"ast": 3.9000000953674316,
"stl": 0.800000011920929,
"blk": 0.3,
"fg3m": 1.7999999523162842
},
"actual": {
"pts": 13,
"reb": 6,
"ast": 1,
"stl": 1,
"blk": 2,
"fg3m": 2
}
},
{
"player": "Immanuel Quickley",
"abbr": "TOR",
"mp": 33.6,
"proj": {
"pts": 16.5,
"reb": 4.800000190734863,
"ast": 6.0,
"stl": 1.2000000476837158,
"blk": 0.0,
"fg3m": 2.5
},
"actual": {
"pts": 23,
"reb": 5,
"ast": 8,
"stl": 1,
"blk": 0,
"fg3m": 6
}
},
{
"player": "Naz Reid",
"abbr": "MIN",
"mp": 28.6,
"proj": {
"pts": 14.800000190734863,
"reb": 6.300000190734863,
"ast": 2.4000000953674316,
"stl": 0.8999999761581421,
"blk": 1.6,
"fg3m": 2.4000000953674316
},
"actual": {
"pts": 17,
"reb": 8,
"ast": 3,
"stl": 1,
"blk": 0,
"fg3m": 4
}
},
{
"player": "Jaden McDaniels",
"abbr": "MIN",
"mp": 39.7,
"proj": {
"pts": 14.800000190734863,
"reb": 4.300000190734863,
"ast": 2.700000047683716,
"stl": 0.8999999761581421,
"blk": 0.9,
"fg3m": 1.7999999523162842
},
"actual": {
"pts": 19,
"reb": 1,
"ast": 4,
"stl": 0,
"blk": 2,
"fg3m": 1
}
},
{
"player": "Sandro Mamukelashvili",
"abbr": "TOR",
"mp": 31.6,
"proj": {
"pts": 11.800000190734863,
"reb": 5.5,
"ast": 2.200000047683716,
"stl": 0.800000011920929,
"blk": 0.7,
"fg3m": 1.600000023841858
},
"actual": {
"pts": 14,
"reb": 4,
"ast": 2,
"stl": 0,
"blk": 1,
"fg3m": 2
}
},
{
"player": "Donte DiVincenzo",
"abbr": "MIN",
"mp": 31.0,
"proj": {
"pts": 11.600000381469727,
"reb": 4.099999904632568,
"ast": 3.9000000953674316,
"stl": 1.2999999523162842,
"blk": 0.7,
"fg3m": 2.9000000953674316
},
"actual": {
"pts": 15,
"reb": 6,
"ast": 5,
"stl": 0,
"blk": 0,
"fg3m": 5
}
},
{
"player": "Rudy Gobert",
"abbr": "MIN",
"mp": 32.9,
"proj": {
"pts": 10.5,
"reb": 10.399999618530273,
"ast": 1.600000023841858,
"stl": 0.800000011920929,
"blk": 1.4,
"fg3m": 0.0
},
"actual": {
"pts": 10,
"reb": 12,
"ast": 2,
"stl": 1,
"blk": 1,
"fg3m": 0
}
},
{
"player": "Collin Murray-Boyles",
"abbr": "TOR",
"mp": 25.3,
"proj": {
"pts": 9.199999809265137,
"reb": 6.099999904632568,
"ast": 2.5,
"stl": 1.0,
"blk": 1.9,
"fg3m": 0.30000001192092896
},
"actual": {
"pts": 13,
"reb": 4,
"ast": 3,
"stl": 2,
"blk": 1,
"fg3m": 1
}
},
{
"player": "Bones Hyland",
"abbr": "MIN",
"mp": 26.0,
"proj": {
"pts": 7.599999904632568,
"reb": 2.0999999046325684,
"ast": 2.5999999046325684,
"stl": 0.6000000238418579,
"blk": 0.1,
"fg3m": 1.2999999523162842
},
"actual": {
"pts": 20,
"reb": 7,
"ast": 3,
"stl": 2,
"blk": 1,
"fg3m": 4
}
},
{
"player": "Jamal Shead",
"abbr": "TOR",
"mp": 22.2,
"proj": {
"pts": 7.199999809265137,
"reb": 2.200000047683716,
"ast": 4.300000190734863,
"stl": 0.800000011920929,
"blk": 0.0,
"fg3m": 1.2000000476837158
},
"actual": {
"pts": 7,
"reb": 2,
"ast": 4,
"stl": 1,
"blk": 1,
"fg3m": 0
}
},
{
"player": "Gradey Dick",
"abbr": "TOR",
"mp": 13.0,
"proj": {
"pts": 7.099999904632568,
"reb": 2.4000000953674316,
"ast": 1.0,
"stl": 0.6000000238418579,
"blk": 0.0,
"fg3m": 1.100000023841858
},
"actual": {
"pts": 6,
"reb": 4,
"ast": 0,
"stl": 0,
"blk": 0,
"fg3m": 0
}
},
{
"player": "Ja'Kobe Walter",
"abbr": "TOR",
"mp": 14.2,
"proj": {
"pts": 6.800000190734863,
"reb": 2.5,
"ast": 1.100000023841858,
"stl": 0.699999988079071,
"blk": 0.3,
"fg3m": 1.100000023841858
},
"actual": {
"pts": 3,
"reb": 0,
"ast": 1,
"stl": 0,
"blk": 0,
"fg3m": 1
}
},
{
"player": "Jaylen Clark",
"abbr": "MIN",
"mp": 6.0,
"proj": null,
"reason": "below_floor",
"actual": {
"pts": 0,
"reb": 0,
"ast": 0,
"stl": 1,
"blk": 0,
"fg3m": 0
}
},
{
"player": "Joe Ingles",
"abbr": "MIN",
"mp": 0.0,
"proj": null,
"reason": "below_floor",
"actual": {
"pts": 0,
"reb": 0,
"ast": 0,
"stl": 0,
"blk": 0,
"fg3m": 0
}
},
{
"player": "Johnny Juzang",
"abbr": "MIN",
"mp": 2.3,
"proj": null,
"reason": "below_floor",
"actual": {
"pts": 0,
"reb": 0,
"ast": 0,
"stl": 0,
"blk": 0,
"fg3m": 0
}
}
]
}
}